CHANGELOG.md
LICENSE
Makefile
README.md
feud/__init__.py
feud/_internal/__init__.py
feud/_internal/_command.py
feud/_internal/_decorators.py
feud/_internal/_docstring.py
feud/_internal/_group.py
feud/_internal/_inflect.py
feud/_internal/_meta.py
feud/_internal/_metaclass.py
feud/_internal/_sections.py
feud/_internal/_types/__init__.py
feud/_internal/_types/click.py
feud/_internal/_types/defaults.py
feud/click/__init__.py
feud/click/context.py
feud/config.py
feud/core/__init__.py
feud/core/command.py
feud/core/group.py
feud/decorators.py
feud/exceptions.py
feud/py.typed
feud/typing/__init__.py
feud/typing/custom.py
feud/typing/pydantic.py
feud/typing/pydantic_extra_types.py
feud/typing/stdlib.py
feud/typing/typing.py
feud/version.py
pyproject.toml
tasks.py
tox.ini
feud-1.0.1.dist-info/LICENSE
feud-1.0.1.dist-info/METADATA
feud-1.0.1.dist-info/WHEEL
feud-1.0.1.dist-info/RECORD
