Metadata-Version: 2.1
Name: feud
Version: 1.0.1
Summary: Build powerful CLIs with simple idiomatic Python, driven by type hints. Not all arguments are bad.
Home-page: https://github.com/eonu/feud
License: MIT
Keywords: python,cli,terminal,command-line,typed,docstrings,typehints,pydantic,click
Author: Edwin Onuonga
Author-email: ed@eonu.net
Maintainer: Edwin Onuonga
Maintainer-email: ed@eonu.net
Requires-Python: >=3.11,<4.0
Classifier: Development Status :: 4 - Beta
Classifier: Environment :: Console
Classifier: Framework :: Pydantic :: 2
Classifier: Intended Audience :: Developers
Classifier: Intended Audience :: Information Technology
Classifier: Intended Audience :: System Administrators
Classifier: License :: OSI Approved :: MIT License
Classifier: Operating System :: OS Independent
Classifier: Programming Language :: Python
Classifier: Programming Language :: Python :: 3
Classifier: Programming Language :: Python :: 3.11
Classifier: Programming Language :: Python :: 3.12
Classifier: Programming Language :: Python :: 3 :: Only
Classifier: Programming Language :: Python :: 3.13
Classifier: Topic :: Software Development :: Libraries :: Application Frameworks
Classifier: Topic :: Software Development :: Libraries :: Python Modules
Classifier: Topic :: Software Development :: User Interfaces
Classifier: Topic :: Terminals
Classifier: Typing :: Typed
Provides-Extra: all
Provides-Extra: email
Provides-Extra: extra-types
Provides-Extra: rich
Requires-Dist: Pydantic[email] (>=2.0.3,<3.0.0)
Requires-Dist: click (>=8.1.0,<9.0.0)
Requires-Dist: docstring-parser (>=0.15,<0.16)
Requires-Dist: packaging (>=24.0,<25.0)
Requires-Dist: pydantic (>=2.0.3,<3.0.0)
Requires-Dist: pydantic-extra-types[phonenumbers,pycountry,python-ulid,semver] (>=2.1.0,<3.0.0) ; extra == "extra-types" or extra == "all"
Requires-Dist: rich-click (>=1.6.1,<2.0.0) ; extra == "rich" or extra == "all"
Project-URL: Documentation, https://feud.readthedocs.io
Project-URL: Repository, https://github.com/eonu/feud
